strangeworks_core/__init__.py
strangeworks_core/utils.py
strangeworks_core/batch/__init__.py
strangeworks_core/batch/utils.py
strangeworks_core/config/__init__.py
strangeworks_core/config/base.py
strangeworks_core/config/config.py
strangeworks_core/config/defaults.py
strangeworks_core/config/env.py
strangeworks_core/config/file.py
strangeworks_core/errors/__init__.py
strangeworks_core/errors/error.py
strangeworks_core/platform/__init__.py
strangeworks_core/platform/auth.py
strangeworks_core/platform/gql.py
strangeworks_core/platform/rest_client.py
strangeworks_core/platform/session.py
strangeworks_core/platform/transport.py
strangeworks_core/types/__init__.py
strangeworks_core/types/backend.py
strangeworks_core/types/base.py
strangeworks_core/types/batch.py
strangeworks_core/types/credentials.py
strangeworks_core/types/file.py
strangeworks_core/types/func.py
strangeworks_core/types/job.py
strangeworks_core/types/machine.py
strangeworks_core/types/product.py
strangeworks_core/types/resource.py
strangeworks_core-0.5.1.dist-info/METADATA
strangeworks_core-0.5.1.dist-info/WHEEL
strangeworks_core-0.5.1.dist-info/RECORD
