Metadata-Version: 2.4
Name: strangeworks-core
Version: 0.5.1
Summary: Strangeworks Core provides the infrastructure to interact with the platform.
Author-email: Strange Devs <hello@strangeworks.com>
Requires-Python: >=3.11
Requires-Dist: deprecated>=1.2.18
Requires-Dist: dill>=0.4.0
Requires-Dist: gql==3.5.3
Requires-Dist: pydantic>=2.11.7
Requires-Dist: requests-toolbelt>=1.0.0
Requires-Dist: requests>=2.32.5
Requires-Dist: tomlkit>=0.13.3
